Workbook
Name CatalogCode: Catalog!$B$4:$B$1296
Name CatalogCost: Catalog!$D$4:$D$1296
Name CatalogDesc: Catalog!$C$4:$C$1296
Name CatalogDisplay: Catalog!$E$4:$E$1296
Name CatalogSearchKey: Catalog!$F$4:$F$1296
Name CatalogSupp: Catalog!$A$4:$A$1296
Name ProductList: Catalog!$E$4:$E$1296

Sheet Estimation
A1: DRY FIRE - Estimation Workbook
A2: Site Address
A3: Quote No
A4: Item Description / Scope | B4: Product | C4: Quantity | D4: Cost (ea) | E4: Sell (ea) | F4: Markup % | G4: Subtotal | H4: Profit
A5: Detector Supply only (Female Toilets) | B5: 2251CPI-W — AA Photoelectric C Series Smoke Detector — White (Pertronic) | C5: 3 | D5: =IFERROR(IF(B5="","",INDEX(CatalogCost,MATCH(B5,CatalogDisplay,0))),"") -> 113.5 | E5: =IF(OR(D5="",D5=0),"",D5*(1+F5)) -> 147.55 | F5: 0.3 | G5: =IF(OR(E5="",C5="",C5=0),"",E5*C5) -> 442.65 | H5: =IF(OR(E5="",C5="",C5=0),"",(E5-D5)*C5) -> 102.15 | J5: 2 | K5: Adjacent the Lift
A6: Detector Supply only (Within Level 5 Tenancy) | B6: 2251CPI-W — AA Photoelectric C Series Smoke Detector — White (Pertronic) | C6: 16 | D6: =IFERROR(IF(B6="","",INDEX(CatalogCost,MATCH(B6,CatalogDisplay,0))),"") -> 113.5 | E6: =IF(OR(D6="",D6=0),"",D6*(1+F6)) -> 147.55 | F6: 0.3 | G6: =IF(OR(E6="",C6="",C6=0),"",E6*C6) -> 2360.8 | H6: =IF(OR(E6="",C6="",C6=0),"",(E6-D6)*C6) -> 544.8 | J6: 16 | K6: Within the tenancies
A7: Detector Supply ( Adjacent the lifts) | B7: 2251CPI-W — AA Photoelectric C Series Smoke Detector — White (Pertronic) | C7: 3 | D7: =IFERROR(IF(B7="","",INDEX(CatalogCost,MATCH(B7,CatalogDisplay,0))),"") -> 113.5 | E7: =IF(OR(D7="",D7=0),"",D7*(1+F7)) -> 147.55 | F7: 0.3 | G7: =IF(OR(E7="",C7="",C7=0),"",E7*C7) -> 442.65 | H7: =IF(OR(E7="",C7="",C7=0),"",(E7-D7)*C7) -> 102.15 | J7: 3 | K7: Within the Male/Female Toilets
A8: Labour Rate 2 x techs | C8: 16 | D8: 105 | E8: 130 | F8: 0.3 | G8: =IF(OR(E8="",C8="",C8=0),"",E8*C8) -> 2080 | H8: =IF(OR(E8="",C8="",C8=0),"",(E8-D8)*C8) -> 400
A9: Consumables | C9: 1 | D9: 200 | E9: 450 | F9: 0.3 | G9: =IF(OR(E9="",C9="",C9=0),"",E9*C9) -> 450 | H9: =IF(OR(E9="",C9="",C9=0),"",(E9-D9)*C9) -> 250
A10: Programming | C10: 1 | D10: 0 | E10: 750 | F10: 0.3 | G10: =IF(OR(E10="",C10="",C10=0),"",E10*C10) -> 750 | H10: =IF(OR(E10="",C10="",C10=0),"",(E10-D10)*C10) -> 750
D11: =IFERROR(IF(B11="","",INDEX(CatalogCost,MATCH(B11,CatalogDisplay,0))),"") | E11: =IF(OR(D11="",D11=0),"",D11*(1+F11)) | F11: 0.3 | G11: =IF(OR(E11="",C11="",C11=0),"",E11*C11) | H11: =IF(OR(E11="",C11="",C11=0),"",(E11-D11)*C11)
D12: =IFERROR(IF(B12="","",INDEX(CatalogCost,MATCH(B12,CatalogDisplay,0))),"") | E12: =IF(OR(D12="",D12=0),"",D12*(1+F12)) | F12: 0.3 | G12: =IF(OR(E12="",C12="",C12=0),"",E12*C12) | H12: =IF(OR(E12="",C12="",C12=0),"",(E12-D12)*C12)
D13: =IFERROR(IF(B13="","",INDEX(CatalogCost,MATCH(B13,CatalogDisplay,0))),"") | E13: =IF(OR(D13="",D13=0),"",D13*(1+F13)) | F13: 0.3 | G13: =IF(OR(E13="",C13="",C13=0),"",E13*C13) | H13: =IF(OR(E13="",C13="",C13=0),"",(E13-D13)*C13)
D14: =IFERROR(IF(B14="","",INDEX(CatalogCost,MATCH(B14,CatalogDisplay,0))),"") | E14: =IF(OR(D14="",D14=0),"",D14*(1+F14)) | F14: 0.3 | G14: =IF(OR(E14="",C14="",C14=0),"",E14*C14) | H14: =IF(OR(E14="",C14="",C14=0),"",(E14-D14)*C14)
A15: TOTAL | G15: =SUM(G5:G14) -> 6526.1 | H15: =SUM(H5:H14) -> 2149.1
A17: FIND PRODUCT
A18: Search term: | E18: Type any part of a code, description, or supplier. Top 15 matches shown below.
A19: Supplier | B19: Code | C19: Description | H19: Cost (AUD)
A20: =IF($B$18="","",IFERROR(INDEX(Catalog!$A$4:$A$1296,MATCH(1,Catalog!$H$4:$H$1296,0)),"")) | B20: =IF($B$18="","",IFERROR(INDEX(Catalog!$B$4:$B$1296,MATCH(1,Catalog!$H$4:$H$1296,0)),"")) | C20: =IF($B$18="","",IFERROR(INDEX(Catalog!$C$4:$C$1296,MATCH(1,Catalog!$H$4:$H$1296,0)),"")) | H20: =IF($B$18="","",IFERROR(INDEX(Catalog!$D$4:$D$1296,MATCH(1,Catalog!$H$4:$H$1296,0)),""))
A21: =IF($B$18="","",IFERROR(INDEX(Catalog!$A$4:$A$1296,MATCH(2,Catalog!$H$4:$H$1296,0)),"")) | B21: =IF($B$18="","",IFERROR(INDEX(Catalog!$B$4:$B$1296,MATCH(2,Catalog!$H$4:$H$1296,0)),"")) | C21: =IF($B$18="","",IFERROR(INDEX(Catalog!$C$4:$C$1296,MATCH(2,Catalog!$H$4:$H$1296,0)),"")) | H21: =IF($B$18="","",IFERROR(INDEX(Catalog!$D$4:$D$1296,MATCH(2,Catalog!$H$4:$H$1296,0)),""))
A22: =IF($B$18="","",IFERROR(INDEX(Catalog!$A$4:$A$1296,MATCH(3,Catalog!$H$4:$H$1296,0)),"")) | B22: =IF($B$18="","",IFERROR(INDEX(Catalog!$B$4:$B$1296,MATCH(3,Catalog!$H$4:$H$1296,0)),"")) | C22: =IF($B$18="","",IFERROR(INDEX(Catalog!$C$4:$C$1296,MATCH(3,Catalog!$H$4:$H$1296,0)),"")) | H22: =IF($B$18="","",IFERROR(INDEX(Catalog!$D$4:$D$1296,MATCH(3,Catalog!$H$4:$H$1296,0)),""))
A23: =IF($B$18="","",IFERROR(INDEX(Catalog!$A$4:$A$1296,MATCH(4,Catalog!$H$4:$H$1296,0)),"")) | B23: =IF($B$18="","",IFERROR(INDEX(Catalog!$B$4:$B$1296,MATCH(4,Catalog!$H$4:$H$1296,0)),"")) | C23: =IF($B$18="","",IFERROR(INDEX(Catalog!$C$4:$C$1296,MATCH(4,Catalog!$H$4:$H$1296,0)),"")) | H23: =IF($B$18="","",IFERROR(INDEX(Catalog!$D$4:$D$1296,MATCH(4,Catalog!$H$4:$H$1296,0)),""))
A24: =IF($B$18="","",IFERROR(INDEX(Catalog!$A$4:$A$1296,MATCH(5,Catalog!$H$4:$H$1296,0)),"")) | B24: =IF($B$18="","",IFERROR(INDEX(Catalog!$B$4:$B$1296,MATCH(5,Catalog!$H$4:$H$1296,0)),"")) | C24: =IF($B$18="","",IFERROR(INDEX(Catalog!$C$4:$C$1296,MATCH(5,Catalog!$H$4:$H$1296,0)),"")) | H24: =IF($B$18="","",IFERROR(INDEX(Catalog!$D$4:$D$1296,MATCH(5,Catalog!$H$4:$H$1296,0)),""))
A25: =IF($B$18="","",IFERROR(INDEX(Catalog!$A$4:$A$1296,MATCH(6,Catalog!$H$4:$H$1296,0)),"")) | B25: =IF($B$18="","",IFERROR(INDEX(Catalog!$B$4:$B$1296,MATCH(6,Catalog!$H$4:$H$1296,0)),"")) | C25: =IF($B$18="","",IFERROR(INDEX(Catalog!$C$4:$C$1296,MATCH(6,Catalog!$H$4:$H$1296,0)),"")) | H25: =IF($B$18="","",IFERROR(INDEX(Catalog!$D$4:$D$1296,MATCH(6,Catalog!$H$4:$H$1296,0)),""))
A26: =IF($B$18="","",IFERROR(INDEX(Catalog!$A$4:$A$1296,MATCH(7,Catalog!$H$4:$H$1296,0)),"")) | B26: =IF($B$18="","",IFERROR(INDEX(Catalog!$B$4:$B$1296,MATCH(7,Catalog!$H$4:$H$1296,0)),"")) | C26: =IF($B$18="","",IFERROR(INDEX(Catalog!$C$4:$C$1296,MATCH(7,Catalog!$H$4:$H$1296,0)),"")) | H26: =IF($B$18="","",IFERROR(INDEX(Catalog!$D$4:$D$1296,MATCH(7,Catalog!$H$4:$H$1296,0)),""))
A27: =IF($B$18="","",IFERROR(INDEX(Catalog!$A$4:$A$1296,MATCH(8,Catalog!$H$4:$H$1296,0)),"")) | B27: =IF($B$18="","",IFERROR(INDEX(Catalog!$B$4:$B$1296,MATCH(8,Catalog!$H$4:$H$1296,0)),"")) | C27: =IF($B$18="","",IFERROR(INDEX(Catalog!$C$4:$C$1296,MATCH(8,Catalog!$H$4:$H$1296,0)),"")) | H27: =IF($B$18="","",IFERROR(INDEX(Catalog!$D$4:$D$1296,MATCH(8,Catalog!$H$4:$H$1296,0)),""))
A28: =IF($B$18="","",IFERROR(INDEX(Catalog!$A$4:$A$1296,MATCH(9,Catalog!$H$4:$H$1296,0)),"")) | B28: =IF($B$18="","",IFERROR(INDEX(Catalog!$B$4:$B$1296,MATCH(9,Catalog!$H$4:$H$1296,0)),"")) | C28: =IF($B$18="","",IFERROR(INDEX(Catalog!$C$4:$C$1296,MATCH(9,Catalog!$H$4:$H$1296,0)),"")) | H28: =IF($B$18="","",IFERROR(INDEX(Catalog!$D$4:$D$1296,MATCH(9,Catalog!$H$4:$H$1296,0)),""))
A29: =IF($B$18="","",IFERROR(INDEX(Catalog!$A$4:$A$1296,MATCH(10,Catalog!$H$4:$H$1296,0)),"")) | B29: =IF($B$18="","",IFERROR(INDEX(Catalog!$B$4:$B$1296,MATCH(10,Catalog!$H$4:$H$1296,0)),"")) | C29: =IF($B$18="","",IFERROR(INDEX(Catalog!$C$4:$C$1296,MATCH(10,Catalog!$H$4:$H$1296,0)),"")) | H29: =IF($B$18="","",IFERROR(INDEX(Catalog!$D$4:$D$1296,MATCH(10,Catalog!$H$4:$H$1296,0)),""))
A30: =IF($B$18="","",IFERROR(INDEX(Catalog!$A$4:$A$1296,MATCH(11,Catalog!$H$4:$H$1296,0)),"")) | B30: =IF($B$18="","",IFERROR(INDEX(Catalog!$B$4:$B$1296,MATCH(11,Catalog!$H$4:$H$1296,0)),"")) | C30: =IF($B$18="","",IFERROR(INDEX(Catalog!$C$4:$C$1296,MATCH(11,Catalog!$H$4:$H$1296,0)),"")) | H30: =IF($B$18="","",IFERROR(INDEX(Catalog!$D$4:$D$1296,MATCH(11,Catalog!$H$4:$H$1296,0)),""))
A31: =IF($B$18="","",IFERROR(INDEX(Catalog!$A$4:$A$1296,MATCH(12,Catalog!$H$4:$H$1296,0)),"")) | B31: =IF($B$18="","",IFERROR(INDEX(Catalog!$B$4:$B$1296,MATCH(12,Catalog!$H$4:$H$1296,0)),"")) | C31: =IF($B$18="","",IFERROR(INDEX(Catalog!$C$4:$C$1296,MATCH(12,Catalog!$H$4:$H$1296,0)),"")) | H31: =IF($B$18="","",IFERROR(INDEX(Catalog!$D$4:$D$1296,MATCH(12,Catalog!$H$4:$H$1296,0)),""))
A32: =IF($B$18="","",IFERROR(INDEX(Catalog!$A$4:$A$1296,MATCH(13,Catalog!$H$4:$H$1296,0)),"")) | B32: =IF($B$18="","",IFERROR(INDEX(Catalog!$B$4:$B$1296,MATCH(13,Catalog!$H$4:$H$1296,0)),"")) | C32: =IF($B$18="","",IFERROR(INDEX(Catalog!$C$4:$C$1296,MATCH(13,Catalog!$H$4:$H$1296,0)),"")) | H32: =IF($B$18="","",IFERROR(INDEX(Catalog!$D$4:$D$1296,MATCH(13,Catalog!$H$4:$H$1296,0)),""))
A33: =IF($B$18="","",IFERROR(INDEX(Catalog!$A$4:$A$1296,MATCH(14,Catalog!$H$4:$H$1296,0)),"")) | B33: =IF($B$18="","",IFERROR(INDEX(Catalog!$B$4:$B$1296,MATCH(14,Catalog!$H$4:$H$1296,0)),"")) | C33: =IF($B$18="","",IFERROR(INDEX(Catalog!$C$4:$C$1296,MATCH(14,Catalog!$H$4:$H$1296,0)),"")) | H33: =IF($B$18="","",IFERROR(INDEX(Catalog!$D$4:$D$1296,MATCH(14,Catalog!$H$4:$H$1296,0)),""))
A34: =IF($B$18="","",IFERROR(INDEX(Catalog!$A$4:$A$1296,MATCH(15,Catalog!$H$4:$H$1296,0)),"")) | B34: =IF($B$18="","",IFERROR(INDEX(Catalog!$B$4:$B$1296,MATCH(15,Catalog!$H$4:$H$1296,0)),"")) | C34: =IF($B$18="","",IFERROR(INDEX(Catalog!$C$4:$C$1296,MATCH(15,Catalog!$H$4:$H$1296,0)),"")) | H34: =IF($B$18="","",IFERROR(INDEX(Catalog!$D$4:$D$1296,MATCH(15,Catalog!$H$4:$H$1296,0)),""))

Sheet Catalog
A1: CATALOG — Consolidated Product List (auto-built from supplier tabs)
A3: Supplier | B3: Code | C3: Description | D3: Cost (AUD ex GST) | E3: Display (used by dropdown) | F3: SearchKey | G3: Match | H3: Rank
A4: Pertronic | B4: F220-A0.6/5A | C4: F220, 600mm Cabinet, 2 Loops, 5A PSU, White rackplates | D4: 4150 | E4: F220-A0.6/5A — F220, 600mm Cabinet, 2 Loops, 5A PSU, White rackplates (Pertronic) | F4: pertronic f220-a0.6/5a f220, 600mm cabinet, 2 loops, 5a psu, white rackplates | G4: =IF(Estimation!$B$18="",0,IF(ISNUMBER(SEARCH(LOWER(Estimation!$B$18),F4)),1,0)) -> 0 | H4: =IF(G4=1,SUM($G$4:G4),"")
A5: Pertronic | B5: F220-A0.6/11A | C5: F220, 600mm Cabinet, 2 Loops, 11A PSU, White rackplates | D5: 4391 | E5: F220-A0.6/11A — F220, 600mm Cabinet, 2 Loops, 11A PSU, White rackplates (Pertronic) | F5: pertronic f220-a0.6/11a f220, 600mm cabinet, 2 loops, 11a psu, white rackplates | G5: =IF(Estimation!$B$18="",0,IF(ISNUMBER(SEARCH(LOWER(Estimation!$B$18),F5)),1,0)) -> 0 | H5: =IF(G5=1,SUM($G$4:G5),"")
A6: Pertronic | B6: F220-A10U/5A | C6: F220, 10U Cabinet, 2 Loops, 5A PSU | D6: 3900 | E6: F220-A10U/5A — F220, 10U Cabinet, 2 Loops, 5A PSU (Pertronic) | F6: pertronic f220-a10u/5a f220, 10u cabinet, 2 loops, 5a psu | G6: =IF(Estimation!$B$18="",0,IF(ISNUMBER(SEARCH(LOWER(Estimation!$B$18),F6)),1,0)) -> 0 | H6: =IF(G6=1,SUM($G$4:G6),"")
A7: Pertronic | B7: F220-A13U/5A | C7: F220, 13U Cabinet, 2 Loops, 5A PSU | D7: 3990 | E7: F220-A13U/5A — F220, 13U Cabinet, 2 Loops, 5A PSU (Pertronic) | F7: pertronic f220-a13u/5a f220, 13u cabinet, 2 loops, 5a psu | G7: =IF(Estimation!$B$18="",0,IF(ISNUMBER(SEARCH(LOWER(Estimation!$B$18),F7)),1,0)) -> 0 | H7: =IF(G7=1,SUM($G$4:G7),"")
A8: Pertronic | B8: F220-A13U/5A-NOASE | C8: F220, 13U, 5A PSU, 8WCOMR, No ASE | D8: 5872 | E8: F220-A13U/5A-NOASE — F220, 13U, 5A PSU, 8WCOMR, No ASE (Pertronic) | F8: pertronic f220-a13u/5a-noase f220, 13u, 5a psu, 8wcomr, no ase | G8: =IF(Estimation!$B$18="",0,IF(ISNUMBER(SEARCH(LOWER(Estimation!$B$18),F8)),1,0)) -> 0 | H8: =IF(G8=1,SUM($G$4:G8),"")
A9: Pertronic | B9: F220-A13U/5A/EA60 | C9: F220, 13U, 5A PSU, 60W Amp+Mic | D9: 4853 | E9: F220-A13U/5A/EA60 — F220, 13U, 5A PSU, 60W Amp+Mic (Pertronic) | F9: pertronic f220-a13u/5a/ea60 f220, 13u, 5a psu, 60w amp+mic | G9: =IF(Estimation!$B$18="",0,IF(ISNUMBER(SEARCH(LOWER(Estimation!$B$18),F9)),1,0)) -> 0 | H9: =IF(G9=1,SUM($G$4:G9),"")
A10: Pertronic | B10: F220-A13U/11A | C10: F220, 13U Cabinet, 2 Loops, 11A PSU | D10: 4231 | E10: F220-A13U/11A — F220, 13U Cabinet, 2 Loops, 11A PSU (Pertronic) | F10: pertronic f220-a13u/11a f220, 13u cabinet, 2 loops, 11a psu | G10: =IF(Estimation!$B$18="",0,IF(ISNUMBER(SEARCH(LOWER(Estimation!$B$18),F10)),1,0)) -> 0 | H10: =IF(G10=1,SUM($G$4:G10),"")
A11: Pertronic | B11: F220-A13U/11A/EA60 | C11: F220, 13U, 11A PSU, 60W Amp+Mic | D11: 5094 | E11: F220-A13U/11A/EA60 — F220, 13U, 11A PSU, 60W Amp+Mic (Pertronic) | F11: pertronic f220-a13u/11a/ea60 f220, 13u, 11a psu, 60w amp+mic | G11: =IF(Estimation!$B$18="",0,IF(ISNUMBER(SEARCH(LOWER(Estimation!$B$18),F11)),1,0)) -> 0 | H11: =IF(G11=1,SUM($G$4:G11),"")
A12: Pertronic | B12: F220-A16U/5A | C12: F220, 16U Cabinet, 2 Loops, 5A PSU | D12: 4730 | E12: F220-A16U/5A — F220, 16U Cabinet, 2 Loops, 5A PSU (Pertronic) | F12: pertronic f220-a16u/5a f220, 16u cabinet, 2 loops, 5a psu | G12: =IF(Estimation!$B$18="",0,IF(ISNUMBER(SEARCH(LOWER(Estimation!$B$18),F12)),1,0)) -> 0 | H12: =IF(G12=1,SUM($G$4:G12),"")
A13: Pertronic | B13: F220-A16U/5A/EA60 | C13: F220, 16U, 5A PSU, 60W Amp+Mic | D13: 5593 | E13: F220-A16U/5A/EA60 — F220, 16U, 5A PSU, 60W Amp+Mic (Pertronic) | F13: pertronic f220-a16u/5a/ea60 f220, 16u, 5a psu, 60w amp+mic | G13: =IF(Estimation!$B$18="",0,IF(ISNUMBER(SEARCH(LOWER(Estimation!$B$18),F13)),1,0)) -> 0 | H13: =IF(G13=1,SUM($G$4:G13),"")
A14: Pertronic | B14: F220-A16U/5A/NCU | C14: F220, 16U, 5A PSU, Network Control Unit | D14: 5411 | E14: F220-A16U/5A/NCU — F220, 16U, 5A PSU, Network Control Unit (Pertronic) | F14: pertronic f220-a16u/5a/ncu f220, 16u, 5a psu, network control unit | G14: =IF(Estimation!$B$18="",0,IF(ISNUMBER(SEARCH(LOWER(Estimation!$B$18),F14)),1,0)) -> 0 | H14: =IF(G14=1,SUM($G$4:G14),"")
A15: Pertronic | B15: F220-A16U/11A | C15: F220, 16U Cabinet, 2 Loops, 11A PSU | D15: 4971 | E15: F220-A16U/11A — F220, 16U Cabinet, 2 Loops, 11A PSU (Pertronic) | F15: pertronic f220-a16u/11a f220, 16u cabinet, 2 loops, 11a psu | G15: =IF(Estimation!$B$18="",0,IF(ISNUMBER(SEARCH(LOWER(Estimation!$B$18),F15)),1,0)) -> 0 | H15: =IF(G15=1,SUM($G$4:G15),"")
... A1296: ESA (EWP) | B1296: 45ft Electric Knuckle Boom (To Site) | C1296: 45ft Electric Knuckle Boom — Electric Knuckle Boom (To Site Base Rate ex GST/levies) | D1296: 240 | E1296: 45ft Electric Knuckle Boom (To Site) — 45ft Electric Knuckle Boom — Electric Knuckle Boom (To Site Base Rate ex GST/levies) (ESA (EWP)) | F1296: esa (ewp) 45ft electric knuckle boom (to site) 45ft electric knuckle boom — electric knuckle boom (to site base rate ex gst/levies) | G1296: =IF(Estimation!$B$18="",0,IF(ISNUMBER(SEARCH(LOWER(Estimation!$B$18),F1296)),1,0)) -> 0 | H1296: =IF(G1296=1,SUM($G$4:G1296),"")

Sheet Pertronic
A1: PERTRONIC INDUSTRIES Pty Ltd — Trade Price List (AUD excl. GST) | Effective 1 April 2025
A2: Prices may change without notice. Special/project pricing available — contact local Pertronic office. All prices in AUD excl. GST and freight.
A3: Category | B3: Product Code | C3: Description | D3: List Price (AUD) | E3: Notes
A4: F220 Panels — 600mm | B4: F220-A0.6/5A | C4: F220, 600mm Cabinet, 2 Loops, 5A PSU, White rackplates | D4: 4150 | E4: 600H x 450W x 155D mm
A5: F220 Panels — 600mm | B5: F220-A0.6/11A | C5: F220, 600mm Cabinet, 2 Loops, 11A PSU, White rackplates | D5: 4391
A6: F220 Panels — 10U | B6: F220-A10U/5A | C6: F220, 10U Cabinet, 2 Loops, 5A PSU | D6: 3900 | E6: Incl. LCD; 530H x 550W x 185D mm
A7: F220 Panels — 13U | B7: F220-A13U/5A | C7: F220, 13U Cabinet, 2 Loops, 5A PSU | D7: 3990 | E7: 600H x 550W x 185D mm
A8: F220 Panels — 13U | B8: F220-A13U/5A-NOASE | C8: F220, 13U, 5A PSU, 8WCOMR, No ASE | D8: 5872
A9: F220 Panels — 13U | B9: F220-A13U/5A/EA60 | C9: F220, 13U, 5A PSU, 60W Amp+Mic | D9: 4853
A10: F220 Panels — 13U | B10: F220-A13U/11A | C10: F220, 13U Cabinet, 2 Loops, 11A PSU | D10: 4231
A11: F220 Panels — 13U | B11: F220-A13U/11A/EA60 | C11: F220, 13U, 11A PSU, 60W Amp+Mic | D11: 5094
A12: F220 Panels — 16U | B12: F220-A16U/5A | C12: F220, 16U Cabinet, 2 Loops, 5A PSU | D12: 4730 | E12: 800H x 575W x 185D mm
A13: F220 Panels — 16U | B13: F220-A16U/5A/EA60 | C13: F220, 16U, 5A PSU, 60W Amp+Mic | D13: 5593
A14: F220 Panels — 16U | B14: F220-A16U/5A/NCU | C14: F220, 16U, 5A PSU, Network Control Unit | D14: 5411
A15: F220 Panels — 16U | B15: F220-A16U/11A | C15: F220, 16U Cabinet, 2 Loops, 11A PSU | D15: 4971
A16: F220 Panels — 16U | B16: F220-A16U/11A/EA60 | C16: F220, 16U, 11A PSU, 60W Amp+Mic | D16: 5834
A17: F220 Panels — 16U | B17: F220-A16U/11A/EA120 | C17: F220, 16U, 11A PSU, 120W Amp+Mic | D17: 6049
A18: F220 Panels — 16U | B18: F220-A16U/11A/NCU | C18: F220, 16U, 11A PSU, Network Control Unit | D18: 5652
A19: F220 Panels — 16U | B19: F220-A16U/22A | C19: F220, 16U Cabinet, 2 Loops, 22A PSU | D19: 5188
A20: F220 Panels — 16U | B20: F220-A16U/22A/EA120 | C20: F220, 16U, 22A PSU, 120W Amp+Mic | D20: 6266
A21: F220 Panels — 22U | B21: F220-A22U/5A | C21: F220, 22U Cabinet, 2 Loops, 5A PSU | D21: 6065 | E21: 1065H x 575W x 290D mm
A22: F220 Panels — 22U | B22: F220-A22U/5A/EA60 | C22: F220, 22U, 5A PSU, 60W Amp+Mic | D22: 6929
A23: F220 Panels — 22U | B23: F220-A22U/11A | C23: F220, 22U Cabinet, 2 Loops, 11A PSU | D23: 6306
A24: F220 Panels — 22U | B24: F220-A22U/11A/EA60 | C24: F220, 22U, 11A PSU, 60W Amp+Mic | D24: 7170
A25: F220 Panels — 22U | B25: F220-A22U/11A/EA120 | C25: F220, 22U, 11A PSU, 120W Amp+Mic | D25: 7386
A26: F220 Panels — 22U | B26: F220-A22U/22A | C26: F220, 22U Cabinet, 2 Loops, 22A PSU | D26: 6523
A27: F220 Panels — 22U | B27: F220-A22U/22A/EA60 | C27: F220, 22U, 22A PSU, 60W Amp+Mic | D27: 7386
A28: F220 Panels — 22U | B28: F220-A22U/22A/EA120 | C28: F220, 22U, 22A PSU, 120W Amp+Mic | D28: 7601
A29: F220 Panels — 28U Slim | B29: F220-A28US/5A | C29: F220, 28U Slim Cabinet, 2 Loops, 5A PSU | D29: 6475 | E29: 1330H x 575W x 290D mm
A30: F220 Panels — 28U Slim | B30: F220-A28US/11A | C30: F220, 28U Slim Cabinet, 2 Loops, 11A PSU | D30: 6717
A31: F220 Panels — 28U Slim | B31: F220-A28US/22A | C31: F220, 28U Slim Cabinet, 2 Loops, 22A PSU | D31: 6932
A32: F220 Panels — 28U | B32: F220-A28U/5A | C32: F220, 28U Cabinet, 2 Loops, 5A PSU | D32: 6475 | E32: 1330H x 575W x 385D mm
A33: F220 Panels — 28U | B33: F220-A28U/11A | C33: F220, 28U Cabinet, 2 Loops, 11A PSU | D33: 6717
A34: F220 Panels — 28U | B34: F220-A28U/22A | C34: F220, 28U Cabinet, 2 Loops, 22A PSU | D34: 6932
A35: F220 Panels — 40U | B35: F220-A40U/5A | C35: F220, 40U Cabinet, 2 Loops, 5A PSU | D35: 7102 | E35: 1865H x 575W x 385D mm
A36: F220 Panels — 40U | B36: F220-A40U/11A | C36: F220, 40U Cabinet, 2 Loops, 11A PSU | D36: 7342
A37: F220 Panels — 40U | B37: F220-A40U/22A | C37: F220, 40U Cabinet, 2 Loops, 22A PSU | D37: 7559
A38: F220 Panels — ARC | B38: F220-A10U/5A-ARC | C38: F220, 10U, 5A PSU c/w ARC | D38: 4442 | E38: Agent Release Controller
A39: F220 Panels — ARC | B39: F220-A13U/5A-ARC | C39: F220, 13U, 5A PSU c/w ARC | D39: 4698
A40: F220 Panels — ARC | B40: F220-A16U/5A-ARC | C40: F220, 16U, 5A PSU c/w ARC | D40: 5364
A41: F220 Panels — ARC | B41: F220-A16U/11A-ARC | C41: F220, 16U, 11A PSU c/w ARC | D41: 5605
A42: F220 Panels — ARC | B42: F220-A28U/5A-ARC | C42: F220, 28U, 5A PSU c/w ARC | D42: 6504
A43: F220 Panels — ARC | B43: F220-A28U/11A-ARC | C43: F220, 28U, 11A PSU c/w ARC | D43: 6745
A44: Panel Accessories | B44: F120P2LMB-A | C44: F120A/F220 2 Loop Driver Mini Board V1.16 | D44: 907
A45: Panel Accessories | B45: LPSNUB | C45: Loop Snubber PCB Assembly | D45: 20
A46: Display Mimics | B46: F220-FFMA | C46: F220 LCD Full Function Mimic AUS | D46: 1260
A47: Display Mimics | B47: F220-AMMA | C47: F220 Alarm Mini-Mimic AUS | D47: 835
A48: Display Mimics | B48: F220-EMMA | C48: F220 Enhanced Mini-Mimic AUS | D48: 877
A49: Display Mimics | B49: MINIMIMIC | C49: F100A/F120A LCD Mini Mimic with Next & Buzzer Mute | D49: 599
A50: Display Mimics | B50: FIREMAP | C50: FireMap Graphics Software Licence | D50: 7000
... A60: Modules — F100A/F220 | B60: ZMB24V | C60: Zonal Bell Monitor Board 24V | D60: 185
A61: Modules — System Sensor | B61: M500DMR | C61: AA Dual Input/Output Module | D61: 277 | E61: Uses M200E-SMB Box
A62: Modules — System Sensor | B62: M500M | C62: AA Single Input Module | D62: 102 | E62: Uses PMB125
A63: Modules — System Sensor | B63: M500R | C63: AA Single Relay Output Module | D63: 120 | E63: Uses PMB125
A64: Modules — System Sensor | B64: M500S | C64: AA Single Supervised Relay Output Module | D64: 120 | E64: Uses PMB125
A65: Modules — System Sensor | B65: M501M | C65: AA Single Input Mini Module | D65: 78
A66: Modules — System Sensor | B66: M500X | C66: Loop Isolator Module | D66: 85
A67: Modules — System Sensor | B67: ISO524-1 | C67: Short Circuit Isolator Single Euro | D67: 54
A68: Modules — System Sensor | B68: M200E-SMB | C68: Surface Mount Box for 200 Series Modules | D68: 19.25
A69: Fan Controls | B69: FCM | C69: Fan Control Module (AS1670.1-2018) | D69: 165
A70: Fan Controls | B70: FCRLY | C70: Fan Control Relay 125x125x56mm Enclosure | D70: 195
A71: Fan Controls | B71: FCRM | C71: Fan Control Repeater Module (AS1670.1-2018) | D71: 175
A72: Fan Controls | B72: FCRESETU | C72: Fan Control Reset Unit (AS1670.1-2018) | D72: 185
A73: Fan Controls | B73: FCSU | C73: Fan Control Switch Unit (AS1670.1-2018) | D73: 185
A74: Fan Controls | B74: DCSWU | C74: Damper Control Switch Unit NF/FLT/FIR (AS1670.1-2018) | D74: 185
A75: Fan Controls | B75: DCSRU | C75: Damper Control Repeater Unit NF/FLT/FIR Indication only | D75: 145
A76: Networking | B76: NET2CARD | C76: F220 Net2 Network Card | D76: 710
... A81: Networking | B81: SPIB-MODBUS | C81: SPIB Interface MODBUS HLI F100/F120/F220 | D81: 3780
A82: Networking | B82: BASGLX-M1 | C82: BASgatewayLX Modbus to BACnet Gateway | D82: 4255 | E82: Requires Modbus GPIB
A83: AA Detectors | B83: 2251CPI-W | C83: AA Photoelectric C Series Smoke Detector — White | D83: 113.5
A84: AA Detectors | B84: 2251CPI-IV | C84: AA Photoelectric C Series Smoke Detector — Ivory | D84: 119
A85: AA Detectors | B85: 2251BPI-BK | C85: AA Photoelectric Smoke Detector — Black | D85: 125
A86: AA Detectors | B86: 2351PTIRAUS-W | C86: AA Photo-Thermal-IR Multi Sensor — White (excl base) | D86: 201 | E86: Acclimate replacement
A87: AA Detectors | B87: 5251CPI-W | C87: AA Fixed Temp Thermal Detector Type B&D — White | D87: 90
A88: AA Detectors | B88: 5251RCPI-W | C88: AA ROR Thermal Detector Type A&C — White | D88: 90
A89: AA Detectors | B89: 5251B-WP | C89: AA Weatherproof Heat Detector Fixed Temp (with B501A base) | D89: 156
A90: AA Detectors | B90: 5251RB-WP | C90: AA Weatherproof Thermal Detector ROR+Fixed Temp | D90: 156
A91: AA Detectors | B91: 7251CPI-W | C91: AA Pinnacle Hi-Sensitivity Smoke C Series — White (excl base) | D91: 479
A92: AA Detectors | B92: CP500 | C92: CP500 Handheld Programmer for AA Weatherproof Detectors | D92: 379
A93: AA Detectors | B93: 22051TLE-34-W | C93: PTIR Multi-Criteria Analogue Smoke — White | D93: 222 | E93: While stocks last
A94: AA Detectors | B94: 2251CTLE-34-IV | C94: COPTIR CO Multi-Criteria Analogue Smoke — Ivory | D94: 396 | E94: While stocks last
A95: AA Detector Bases | B95: B501AUS-W | C95: AA Detector Base — White | D95: 12.25
A96: AA Detector Bases | B96: B501AUS-BK | C96: AA Detector Base — Black | D96: 19.25
A97: AA Detector Bases | B97: B501AP-W | C97: AA Detector Base — White (Addressable Sounder Compatible) | D97: 14
A98: AA Detector Bases | B98: B501AP-BK | C98: AA Detector Base — Black (Addressable Sounder Compatible) | D98: 20
A99: AA Detector Bases | B99: B501BI-W | C99: Isolator Base — Bright White for addressable detector | D99: 53
A100: AA Duct Detection | B100: DNR-AUS | C100: AA Duct Housing, No Relay, No Detector | D100: 253
A101: AA Duct Detection | B101: DNRW | C101: AA Watertight Non-Relay Duct Sampling | D101: 349
A102: AA Duct Detection | B102: DST1.5 | C102: Metal Sampling Tube — Duct Width 0.3–0.6m | D102: 19
A103: AA Duct Detection | B103: DST3 | C103: Metal Sampling Tube — Duct Width 0.6–1.2m | D103: 27.5
A104: AA Duct Detection | B104: DST5 | C104: Metal Sampling Tube — Duct Width 1.2–2.4m | D104: 39.5
A105: AA Duct Detection | B105: DST10 | C105: Metal Sampling Tube — Duct Width 2.4–3.7m | D105: 68
A106: Conv. Detectors | B106: 2151BPI-W | C106: Low Profile Photo Smoke Detector — White (excl base) | D106: 72
... A130: Manual Call Points | B130: PS200 | C130: PS200 Protective Hinged Cover for KAC MCPs | D130: 12
A131: Sounders & Strobes | B131: DSS-PC-I00 | C131: AA Sounder/Strobe Base c/w isolator — Pure White, AS7240.23 | D131: 217 | E131: Requires B501AP-W Base
A132: Sounders & Strobes | B132: WSS-PC-I00 | C132: AA Wall Sounder/Strobe c/w isolator — Pure White, AS7240.23 | D132: 210 | E132: Requires B501AP-W Base
A133: Sounders & Strobes | B133: BSS-DR-N34 | C133: AA Detector Base Sounder-Strobe Red, White Base, Non-Iso | D133: 241 | E133: Requires B501AP-IV Base
A134: Sounders & Strobes | B134: LASS-BSO-NC-W | C134: AA Detector Base Sounder — White, Non-Isolation | D134: 113.5 | E134: Requires B501AUS Base
A135: Sounders & Strobes | B135: LASS-WSO-NC-W | C135: AA Wall Sounder — White, Non-Isolation | D135: 128.5 | E135: Requires B501AUS Base
A136: Sounders & Strobes | B136: LASS-BSS-NC-W | C136: AA Detector Base Sounder-Strobe Red, White Base, Non-Iso | D136: 181 | E136: Requires B501AUS Base
...

Sheet Fusion Fire
A1: FUSION FIRE SYSTEMS — Quote QU30920 | Unit Rates for FlameSafe | 7 April 2026 | Valid 60 days
A2: Contact: Giorgio Montanari | 1300 875 360 | admin@fusionadvanced.com | ABN: 51 159 254 921 | All prices excl. GST and freight.
A3: Category | B3: Item Code | C3: Description | D3: Unit Price (AUD) | E3: Notes
A4: AU-5000 Screen/Cards | B4: MXS-504 | C4: AU-5000 Spare Display Card | D4: 1540
A5: AU-5000 Motherboards | B5: MXS-501V | C5: AU-5000 Spare Single Loop Base Card c/w PSU | D5: 1840
A6: AU-5000 Motherboards | B6: MXS-502V | C6: AU-5000 Spare Two Loop Base Card c/w PSU | D6: 2470
A7: AU-5000 Motherboards | B7: MXS-503V | C7: AU-5000 Spare Four Loop Base Card c/w PSU | D7: 3095
A8: Network Cards | B8: MXP-503 | C8: Axis 5000 Standard Network Card | D8: 385
A9: Network Cards | B9: MXP-509 | C9: Axis 5000 Peer To Peer Fault Tolerant Network Card | D9: 633
A10: Network Cards | B10: MOXA-Fiber-MM | C10: Multi Mode Fiber Optic Converter SC — AdNet Network | D10: 410.46 | E10: Confirm SC or ST on order; 2x per fault-tolerant system; 1x UFEC15 PSE per system
A11: Network Cards | B11: MOXA-Fiber-SM | C11: Single Mode Fibre Optic Converter SC — AdNet Network | D11: 845.25 | E11: Confirm SC or ST on order; 2x per fault-tolerant system; 1x UFEC15 PSE per system
A12: Network Cards | B12: UFEC15-24S | C12: Axis 5000 NT DC-DC Converter 24V to 12V @ 1.25A | D12: 275 | E12: For NT Miri unit
A13: P-Bus Cards | B13: MXP-502 | C13: Axis 5000 Digital Single Loop Driver Card (240 devices) | D13: 700
A14: P-Bus Cards | B14: MXP-544 | C14: Axis 5000 P-Bus 8 Way Relay Card | D14: 271
A15: P-Bus Cards | B15: AUP-543 | C15: Axis 5000 P-Bus 6 Way Fan Controller c/w LEDs/Switches | D15: 911
A16: P-Bus Cards | B16: AUP-538 | C16: Axis 5000 P-Bus 16-Way Switch Input Module c/w 3 Indicators | D16: 903
A17: P-Bus Cards | B17: MXP-536 | C17: Axis 5000 P-Bus 8-Way Conventional Zone Card | D17: 992 | E17: Max 16 cards
A18: Axis Detectors | B18: FWOPX | C18: Digital AA Optical Smoke Detector c/w SCI, Magnet Test | D18: 98 | E18: Drift Compensation; LED Colour Flash optional
A19: Axis Detectors | B19: FWOP | C19: Digital AA Photo Optical Smoke Detector | D19: 92.5 | E19: Automatic Drift Compensation
A20: Axis Detectors | B20: FWOHX | C20: Digital AA Multi-Criteria Detector c/w SCI, Magnet Test | D20: 144 | E20: Drift Compensation; LED Colour Flash optional
A21: Axis Detectors | B21: FWOH | C21: Digital AA Multi-Criteria Detector | D21: 139 | E21: Automatic Drift Compensation
A22: Axis Detectors | B22: FWHTX | C22: Digital AA Thermal Detector ROR/FT c/w SCI, Magnet Test | D22: 100
A23: Axis Detectors | B23: FWHT | C23: Digital AA Thermal Detector ROR or FT | D23: 95
A24: Axis Detectors | B24: FWMB | C24: Standard AA Detector Mounting Base c/w Loop Continuity Clip | D24: 15
A25: Axis Detectors | B25: RI-ICS | C25: Remote Indicator — In Concealed Space | D25: 23
A26: Axis Detectors | B26: FWDDH-OPX | C26: Duct Detector Housing 0.5–20m/s (incl. FWOPX & FWMB) | D26: 440 | E26: Approved AS1603.13, AS7240.7/.17/.13
A27: Axis Detectors | B27: DDH-ST-1.5 | C27: Duct Housing Sampling Tube 1.5m | D27: 135
A28: Thermal Probes | B28: T-1000E-65 | C28: SS Probe Type A Heat Detector 65°C | D28: 340
A29: Manual Call Points | B29: FWCP | C29: Digital AA MCP — Resettable (Red) | D29: 148
A30: Manual Call Points | B30: FCPCI | C30: Transparent Cover for Axis-CP AA MCPs (no text) | D30: 18
A31: Manual Call Points | B31: MCP-RW | C31: Conv. MCP White EWIS c/w Resettable Glass | D31: 27.93
A32: Manual Call Points | B32: MCP-Cover-UK | C32: MCP Clear Cover for VCP100 MCPs | D32: 11.76
A33: Speakers & Strobes | B33: VAD-WWW | C33: Wall VAD White Flash, White Body AS ISO7240.23 24VDC | D33: 105 | E33: Shallow base
A34: Speakers & Strobes | B34: FWCWS | C34: Conventional Wall Sounder | D34: 121
A35: Speakers & Strobes | B35: FWCWSV | C35: Conventional Wall Sounder Beacon | D35: 168
A36: Speakers & Strobes | B36: FWSMB | C36: AA Loop Powered Synchronised Sounder Base — 30 Tones | D36: 234 | E36: Selectable by logic
A37: Speakers & Strobes | B37: FWSVMB | C37: Addressable Sounder Beacon Base — 30 Tones | D37: 285 | E37: Individually addressed from CIE
A38: Speakers & Strobes | B38: FWS2MB | C38: Addressable Synchronised Sounder Base — 32 Tones | D38: 188 | E38: SCI (X) detectors only; AS7240.3
A39: Speakers & Strobes | B39: FWS2AMB | C39: Slave Sounder Base — 32 Selectable Tones | D39: 169 | E39: AS7240.3
A40: Speakers & Strobes | B40: FWSV2MB | C40: Addressable Sounder & VAD Base — 32 Tones | D40: 267 | E40: SCI (X) detectors only; AS7240.3 & 23
A41: Speakers & Strobes | B41: FWLID200/W | C41: Sounder Base Cover (White) — Axis & Taurus Sounder Bases | D41: 10
A42: Speakers & Strobes | B42: VA-104C | C42: 100mm 6W Metal Grill Recessed Ceiling Speaker AS7240.24 | D42: 50 | E42: 155mm cut-out required
A43: Speakers & Strobes | B43: HS-155 | C43: 155mm Metal & Wood Hole Saw Bit for VA-104 Speakers | D43: 64.68
A44: Speakers & Strobes | B44: C2160 | C44: Low Profile 100mm 5W EWIS Recessed Ceiling Speaker AS7240.24 | D44: 66
A45: Speakers & Strobes | B45: CF-0703 | C45: Low Profile 100mm 5W EWIS Surface Mount Speaker AS7240.24 | D45: 90 | E45: Requires equalisation to comply
A46: Speakers & Strobes | B46: CF2053G | C46: 10W EWIS Horn Speaker Grey AS7240.24 | D46: 84.53
A47: Modules | B47: FMMC-120 | C47: Mini Single Relay Output Module (Form C) — No Enclosure | D47: 152 | E47: AS7240.17 & 18
A48: Modules | B48: FMIC-100 | C48: Single Input & Output Module Supervised — Wall Mount | D48: 189 | E48: Requires DMB enclosure
A49: Modules | B49: FMMI-100 | C49: Mini Single Input Module Supervised — No Enclosure | D49: 182 | E49: AS7240.17 & 18
A50: Modules | B50: FMMIC-100 | C50: Mini Single I/O Module Supervised — No Enclosure | D50: 184 | E50: AS7240.17 & 18
A51: Modules | B51: FMMIC-120 | C51: Mini Single I/O Relay Module (Form C) — No Enclosure | D51: 190 | E51: AS7240.17 & 18
A52: Modules | B52: FMMC-100 | C52: Mini Single Output Module Supervised — No Enclosure | D52: 182 | E52: AS7240.17 & 18
A53: Modules | B53: FMI-100 | C53: Single Input Module Supervised — Wall Mount | D53: 182 | E53: Requires DMB enclosure
A54: Modules | B54: FMC-120 | C54: Single Relay Output Module (Form C) — Wall Mount | D54: 183.5 | E54: Requires DMB enclosure
A55: Modules | B55: FMIC-120 | C55: Single Input & Relay Output Module (Form C) — Wall Mount | D55: 189 | E55: Requires DMB enclosure
A56: Modules | B56: DMB100-C | C56: PVC Mounting Box for VM Modules 86x86x43mm | D56: 11.2
A57: Modules | B57: FMIC-404 | C57: 4 Supervised Input & 4 Relay Output Module c/w Enclosure | D57: 310
A58: Modules | B58: FMCZ100 | C58: Collective/Conv. Zone Input Module — Loop Powered, Wall Mount | D58: 130 | E58: 1x C/O contact
A59: Door Holders | B59: MDH-003 | C59: Magnetic Door Holder 25/50kg — Wall Mount | D59: 60.75
A60: Door Holders | B60: MDH-1350 | C60: Magnetic Door Holder 25/50kg — Wall Mount | D60: 69.83
A61: EWIS | B61: WIP Phone | C61: Red Warded Intercom Phone | D61: 200
A62: EWIS | B62: WIP-120 | C62: Addressable Warden Intercom Phone Module c/w Speech Loop | D62: 350 | E62: WIP Phone required
A63: Taurus Wireless | B63: FRMT | C63: TAURUS Wireless DDI AA Translator/Transmitter — 128 Device | D63: 686 | E63: 32 local; 15x FRME expanders; AS7240.25/.17/.18
A64: Taurus Wireless | B64: FRMEC | C64: TAURUS Wireless DDI Conv. Transmitter Interface — 32 Device | D64: 863 | E64: AS7240.25/.17/.18
A65: Taurus Wireless | B65: FRME | C65: TAURUS Wireless DDI Expander Module — 32 Device | D65: 396 | E65: AS7240.25
A66: Taurus Wireless | B66: FROP | C66: TAURUS Wireless Dual Photo Optical Smoke Detector | D66: 300 | E66: AS7240.25 & 7240.7
A67: Taurus Wireless | B67: FROH | C67: TAURUS Wireless Multi-Criteria & Multi-Sensor Detector | D67: 325 | E67: AS7240.25/.5/.7
A68: Taurus Wireless | B68: FRHT | C68: TAURUS Wireless Thermal Detector — ROR or Fixed Temp | D68: 290 | E68: AS7240.25 & 7240.5
A69: Taurus Wireless | B69: FRMI | C69: TAURUS Wireless Supervised Single Input Module | D69: 296 | E69: AS7240.25/.18/.13
A70: Taurus Wireless | B70: FRMO | C70: TAURUS Wireless Output Module with Relay | D70: 478 | E70: AS7240.25/.18/.13
A71: Taurus Wireless | B71: FRSMB | C71: TAURUS Wireless Sounder & Base 91dB@1m | D71: 315 | E71: AS7240.25 & 7240.3
A72: Taurus Wireless | B72: FRCP | C72: TAURUS Wireless AA MCP — Resettable | D72: 316 | E72: AS7240.25 & 7240.11
A73: Taurus Wireless | B73: FRWSM | C73: TAURUS Wireless Sounder/VAD Interface Module | D73: 296 | E73: AS7240.25/.18/.13
A74: Tools | B74: FWPU | C74: Fusion Hand-Held Programming Unit (upgradable) | D74: 430 | E74: For hard-wired detectors & modules
A75: Tools | B75: FWPU/CARRY | C75: AXIS-PU Carry Case 245x155x75mm | D75: 14.7
A76: Tools | B76: CR123A-PCCR | C76: Duracell/PROCELL CR-123A 3V Lithium Battery | D76: 9.92 | E76: Price per battery
A77: Tools | B77: DMB100-L | C77: Large PVC Mounting Box for VM Modules 108x108x64mm | D77: 11.03
A78: QUOTE TOTAL (excl. GST) | D78: 27108.97 | E78: + GST $2,710.90 = $29,819.87 total incl. GST

Sheet FlameStop
A1: FLAMESTOP AUSTRALIA Pty Ltd — Web Pricing (AUD excl. GST) | As at 10 April 2026 | www.flamestop.com.au
A2: All prices exclude GST and freight. POA items confirmed upon request. Prices subject to change without notice.
A3: Category | B3: Part Number | C3: Description | D3: Price (AUD) | E3: Notes
A4: VESDA-E VEP | B4: P-VEP-A00-1P | C4: VESDA-E VEP with LEDs, 1 Pipe | D4: 4575
A5: VESDA-E VEP | B5: P-VEP-A00-P | C5: VESDA-E VEP with LEDs, Plastic Enclosure 4 Pipe | D5: 5630
A6: VESDA-E VEP | B6: P-VEP-A10-P | C6: VESDA-E VEP with 3.5" LCD Display, 4 Pipe | D6: 6240
A7: VESDA-E VEP | B7: P-VSP-960 | C7: Mounting Bracket for VEP, VES and VEU | D7: 47.23
A8: VESDA-E VEP | B8: P-VSP-962 | C8: VESDA-E Filter (1 pc) | D8: 98
A9: VESDA-E VEP | B9: P-VSP-962-20 | C9: VESDA-E Filter — 20 Pieces | D9: 1294
A10: VESDA-E VEP | B10: P-VSP-965 | C10: VESDA-E Sampling Module | D10: 513.34
A11: VESDA-E VEP | B11: P-VSP-964-03 | C11: VESDA-E Smoke Detection Chamber for GA3 (Serial 97+) | D11: 2060.23
A12: VESDA-E VES | B12: P-VES-A00-P | C12: VESDA-E VES with LEDs, Plastic Enclosure | D12: 8994
A13: VESDA-E VES | B13: P-VES-A10-P | C13: VESDA-E VES with 3.5 inch Display, Plastic Enclosure | D13: 9635
A14: Batteries — Lead Acid | B14: PLAB1.3AH | C14: 1.3AH 12VDC Lead Acid Battery | D14: 16.75
A15: Batteries — Lead Acid | B15: PLAB2.3AH | C15: 2.3AH 12VDC Lead Acid Battery | D15: 17.91
... A55: Battery Boxes / PSU | B55: PS406-M3D | C55: 24VDC Stand-Alone 5.25A PSU in Metal Cabinet (2x26ah batteries) | D55: 875
A56: Speaker Grills | B56: PWSP-GRILL | C56: White Grill for 100mm Speaker | D56: 3.5 | E56: NOT approved AS ISO 7240.24 — requires project engineer approval
A57: Speaker Grills | B57: PWSP-GRILL200 | C57: White Grill for 200mm Speaker | D57: 5.15 | E57: NOT approved AS ISO 7240.24 — requires project engineer approval
A58: Speaker Grills | B58: PWSP-100PLAIN | C58: 5 Watt 100V 100mm Twin Cone Speaker | D58: 25.52 | E58: NOT approved AS ISO 7240.24 — requires project engineer approval
A59: Speaker Grills | B59: PHS140 | C59: Hole Saw 140mm + Arbor | D59: 77.5
A60: VADs — Ceiling Mount | B60: PVAD-R-CM | C60: Ceiling Mount VAD — Red Body, Red Flash | D60: 90.14
A61: VADs — Ceiling Mount | B61: PVAD-W-CM | C61: Ceiling Mount VAD — White Body, Red Flash | D61: 90.14
A62: VADs — Ceiling Mount | B62: PVAD-W-CM-WF | C62: Ceiling Mount VAD — White Body, White Flash | D62: 90.14
A63: VADs — Ceiling Mount | B63: PVAD-W-CMDB | C63: Ceiling Mount VAD Deep Base — White Body, Red Flash | D63: 90.14
A64: VADs — Ceiling Mount | B64: PVAD-R-CMDB | C64: Ceiling Mount VAD Deep Base — Red Body, Red Flash | D64: 89.86
A65: VADs — Ceiling Mount | B65: PVAD-W-CMDB-WF | C65: Ceiling Mount VAD Deep Base — White Body, White Flash | D65: 90.14
A66: VADs — Wall Mount | B66: PVAD-R-WM | C66: Wall Mount VAD — Red Lens | D66: 86.67
A67: VADs — Wall Mount | B67: PVAD-W-WM | C67: Wall Mount VAD — White Body, Red Flash | D67: 86.67
A68: VADs — Wall Mount | B68: PVAD-R-WMDB | C68: Wall Mount VAD Deep Base — Red Body, Red Flash | D68: 92.45
A69: VADs — Wall Mount | B69: PVAD-R-WMBASE | C69: Red Wall Mount VAD Base Only | D69: 175
A70: VADs — Accessories | B70: PXCRDEEP | C70: Optional Red Deep Base for Conduit Entry | D70: 10.98
... A94: Indoor MCPs | B94: P-SU0624 | C94: MCP RED No Back Box Normally Open Simplex Glass SU0624 | D94: 58.11
A95: Indoor MCPs | B95: P-SU0631 | C95: New MCP KAC RED Manual Call Point SU0631 | D95: POA | E95: POA
A96: Indoor MCPs | B96: P-SU0632 | C96: New MCP KAC RED Manual Call Point Back Box Only SU0632 | D96: 12.72
A97: Indoor MCPs | B97: PMCP-GREEN-DPDT | C97: Green DP/DT Resettable Manual Call Point | D97: 75
A98: Indoor MCPs | B98: PXDC-GREEN-DPTP | C98: Green Double Pole Manual Call Point — Resettable | D98: 85
A99: Indoor MCPs | B99: P-SU0614 | C99: MCP Emergency Door Release Double Pole White | D99: 125
A100: Indoor MCPs | B100: P-FP1114 | C100: MCP Emergency Door Release Double Pole Yellow FP1114 | D100: 85
A101: Indoor MCPs | B101: PSIGN-MCP | C101: Sign for MCP — After Activation Call 000 | D101: 7.02
A102: Indoor MCPs | B102: P-515.001.033 | C102: Weather Stopper Break Seal Kit RED 515.001.033 | D102: 71.51
A103: Indoor MCPs | B103: P-515.001.035 | C103: Weather Stopper II Surface Mount STI3150 515.001.035 | D103: 294
A104: Indoor MCPs | B104: P-515.001.032 | C104: Weather Stopper c/w Sounder 515.001.032 | D104: 346.73
A105: Indoor MCPs | B105: P-SU0622 | C105: IP67 Weatherproof Gasket for SUo612 SU0622 | D105: 17.36
A106: Indoor MCPs | B106: P-FP0331 | C106: MCP NZ Red Wormald 1841 Clean Contact Surface Mount FP0331 | D106: 79.15
A107: Indoor MCPs | B107: P-514.001.109 | C107: CP220 CALLPOINT I.S 514.001.109 | D107: 463.06

Sheet Ampac
A1: AMPAC Pty Ltd — Trade Price List (AUD excl. GST) | Effective 12 May 2025 | ABN: 81 634 063 200 | www.ampac.net
A2: Contact: David Lehn (NSW State Manager) — (02) 8866 6211 | 0417 986 847 | dlehn@ampac.net | Bradley Marshall (Technical Support) — (02) 8866 6215 | 0406 384 319 | Unit B28, 32 Egerton St, Silverwater NSW 2128
A3: Category | B3: Item No. | C3: Description | D3: Trade Price (AUD) | E3: Notes
A4: Conv. FIP — ZoneSense | B4: 2250-4200 | C4: ZoneSense 4 Zone (DH4) BX1 ABS Cabinet | D4: 672
A5: Conv. FIP — ZoneSense | B5: 2250-4250 | C5: ZoneSense 4 Zone (DH4) BX10 Metal Cabinet | D5: 669
A6: Conv. FIP — ZoneSense Plus | B6: 2550-1100 | C6: ZoneSense PLUS 4 Zone ABS Inc Batteries | D6: 873
A7: Conv. FIP — ZoneSense Plus | B7: 2550-1200 | C7: ZoneSense PLUS 8 Zone ABS Inc Batteries | D7: 1014
A8: Conv. FIP — ZoneSense Plus | B8: 2550-2100 | C8: ZoneSense PLUS 4 Zone ABS with Window Inc Batteries | D8: 960
A9: Conv. FIP — ZoneSense Plus | B9: 2550-2200 | C9: ZoneSense PLUS 8 Zone ABS with Window Inc Batteries | D9: 1129
A10: Conv. FIP — Agent Release | B10: 2553-0410-0100 | C10: ZoneSense PLUS 4 Zone SP1X Agent Release Inc Batteries | D10: 2001
A11: Conv. FIP — Agent Release | B11: 2553-0810-0100 | C11: ZoneSense PLUS 8 Zone SP1X Agent Release Inc Batteries (2x7AH) | D11: 2078
A12: AA FIP — LoopSense | B12: 8251-0110 | C12: LoopSense 1 Loop 3A SP1X Apollo AS7240 | D12: 2472
A13: AA FIP — LoopSense | B13: 8251-0210 | C13: LoopSense 2 Loop 3A SP1X Apollo AS7240 | D13: 2865
A14: AA FIP — LoopSense | B14: 8251-0110-1100 | C14: LoopSense 1 Loop 3A SP1X OWS25 Apollo AS7240 | D14: 3256
A15: AA FIP — LoopSense | B15: 8251-0210-1100 | C15: LoopSense 2 Loop 3A SP1X OWS25 Apollo AS7240 | D15: 3658
... A25: AA FIP — FireFinder Plus | B25: 8651-0113-1200 | C25: FireFinder+ 1 Loop OWS50 5A SP8 | D25: 6315
A26: AA FIP — FireFinder Plus | B26: 8651-0117 | C26: FireFinder+ 1 Loop 14A 10U | D26: POA | E26: Contact CSO
A27: AA FIP — FireFinder Plus | B27: 8651-0118 | C27: FireFinder+ 1 Loop 22A 16U | D27: POA | E27: Contact CSO
A28: AA FIP — FireFinder Plus | B28: 8651-0119 | C28: FireFinder+ 1 Loop 22A 29U | D28: POA | E28: Contact CSO
A29: AA FIP — FireFinder Plus Conv | B29: 8653-0810 | C29: FireFinder+ 8 Zone 5A SP1X | D29: 2495
A30: AA FIP — FireFinder Plus Conv | B30: 8653-0810-1100 | C30: FireFinder+ 8 Zone OWS25 5A SP1 | D30: 3352
A31: AA FIP — FireFinder Plus Conv | B31: 8653-0810-1200 | C31: FireFinder+ 8 Zone OWS50 5A SP1 | D31: 3826
A32: AA FIP — FireFinder Plus Conv | B32: 8653-0813 | C32: FireFinder+ 8 Zone 5A SP8X | D32: 3148
A33: AA FIP — FireFinder Plus Conv | B33: 8653-0813-1200 | C33: FireFinder+ 8 Zone OWS50 5A SP8 | D33: 4535
A34: Panel Add-Ons | B34: 4350-0004 | C34: AS7240 Smart Terminal BX1 | D34: POA
A35: Panel Add-Ons | B35: 4350-0005 | C35: AS7240 Smart Terminal BX1 with PSU | D35: POA
A36: Panel Add-Ons | B36: 4350-0006 | C36: AS7240 Smart Terminal Slimline | D36: POA
A37: Panel Add-Ons | B37: 4210-0046 | C37: Wall/Ceiling Mount Surround | D37: POA
A38: Battery Cabinets | B38: 4210-0040 | C38: Battery Cab for SP1X/SP1M (Surfmist) | D38: 267
A39: Battery Cabinets | B39: 4210-0041 | C39: Battery Cab for FFP/LoopSense SP8X (Surfmist) | D39: 341
A40: Battery Cabinets | B40: 4210-0042 | C40: SP1X/M Cabinet Surround Surfmist | D40: 273
A41: Battery Cabinets | B41: 4210-0044 | C41: SP8X Cabinet Surround Surfmist | D41: 341
A42: Battery Cabinets | B42: 4210-0045 | C42: SP8X and Battery Cabinet Surround Surfmist | D42: 416
A43: EWIS — EvacU Elite | B43: 6350-PNL13U | C43: Base Panel 13U EvacU Elite | D43: POA | E43: Contact CSO
A44: EWIS — EvacU Elite | B44: 6350-PNL24U | C44: Base Panel 24U EvacU Elite | D44: POA | E44: Contact CSO
A45: EWIS — EvacU Elite | B45: 6350-PNL24UCOMBO | C45: Base Panel 24U Combo EvacU Elite | D45: POA | E45: Contact CSO
A46: EWIS — EvacU Elite Amps | B46: 6350-HPA150W-CSO | C46: EvacU Elite 150W HPA Card | D46: 1739
A47: EWIS — EvacU Elite Amps | B47: 6350-LPA25W-DUAL-CSO | C47: EvacU Elite Dual 25W Amplifier LPA Card | D47: 667
A48: EWIS — EvacU Elite Amps | B48: 6350-LPA50W-CSO | C48: EvacU Elite 50W LPA Card | D48: 637
A49: EWIS — EvacU Elite Amps | B49: ASS63LWIPS | C49: EvacU Elite Loop WIP | D49: 431
A50: EWIS — EvacU Elite Amps | B50: ASS63WIPS | C50: EvacU Elite Radial WIP | D50: 210
A51: OWS — EvacU OWS | B51: 6010-0001 | C51: OWS 50W Amplifier | D51: 959
A52: OWS — EvacU OWS | B52: 6010-0002 | C52: OWS 25W Amplifier | D52: 489
A53: OWS — EvacU OWS | B53: 6010-0018 | C53: OWS Indicator & Controls | D53: 449
A54: OWS — EvacU OWS | B54: 6050-0010-0800 | C54: EvacU EWCIE 4x50W (200W) 10A | D54: 4010
A55: OWS — EvacU OWS | B55: 6050-0010-1100 | C55: EvacU EWCIE 25W 3A | D55: 1593
A56: OWS — EvacU OWS | B56: 6050-0010-1200 | C56: EvacU EWCIE 50W 3A | D56: 1904
A57: OWS — EvacU OWS | B57: 6050-0010-1400 | C57: EvacU EWCIE 2x50W (100W) 5A | D57: 2628
... A151: Air Sampling — Wagner Heads | B151: AD-10-5195 | C151: ProSens Head 0.01% DeepFreeze -40 to 60°C | D151: 5286
A152: Air Sampling — Wagner Filters | B152: AD-10-1960 | C152: Wagner Filter Box LF-AD 15 Micron (-40 to 60°C) | D152: 455 | E152: Filter box — complete unit
A153: Air Sampling — Wagner Filters | B153: AD-10-1963 | C153: Wagner Filter Box LF-AD-1 10 Micron (-40 to 60°C) | D153: 531 | E153: Filter box — complete unit
A154: Air Sampling — Wagner Filters | B154: AD-10-1966 | C154: Wagner Filter Box LF-AD-2 5 Micron (-40 to 60°C) | D154: 561 | E154: Filter box — complete unit
A155: Air Sampling — Wagner Filters | B155: AD-10-0330 | C155: Wagner Filter Element LF-AD-E 15 Micron (replacement) | D155: 102 | E155: Replacement element for LF-AD filter box
A156: Air Sampling — Wagner Filters | B156: AD-10-0335 | C156: Wagner Filter Element LF-AD-ES 10 Micron (replacement) | D156: 168 | E156: Replacement element for LF-AD-1 filter box
A157: Air Sampling — Wagner Filters | B157: AD-10-0332 | C157: Wagner Filter Element LF-AD-E2 5 Micron (replacement) | D157: 161 | E157: Replacement element for LF-AD-2 filter box
A158: Air Sampling — Wagner Filters | B158: 7010-0134 | C158: 30 Micron Filter Box | D158: 252
A159: Air Sampling — Wagner Misc | B159: AD-10-0005 | C159: ASD Sound Absorber | D159: 383
A160: Air Sampling — Wagner Misc | B160: AD-05-0563 | C160: Wagner Diagnostic Tool — Laptop USB to Wagner | D160: 1590
A161: Air Sampling — MicroSens | B161: AD-05-4531 | C161: MicroSens 0.5% Std PreAlarm | D161: 2386
A162: Air Sampling — MicroSens | B162: AD-05-4539 | C162: MicroSens 0.5% DeepFreeze PreAlarm -40°C | D162: 2862
A163: Air Sampling — MicroSens | B163: 7010-6700 | C163: MicroSens Backbox with I/O Device | D163: 449
A164: Air Sampling — MicroSens | B164: 7010-6701 | C164: MicroSens Backbox (AD-05-3500) | D164: 207
A165: Air Sampling — Fittings | B165: 230-0061 | C165: Pipe (4m Length) | D165: 15 | E165: 25mm ASD pipe
A166: Air Sampling — Fittings | B166: 230-0062 | C166: Pipe Coupling STD DX40025 | D166: 3
A167: Air Sampling — Fittings | B167: 230-0063 | C167: Pipe Coupling IP65 DX43025 | D167: 5
A168: Air Sampling — Fittings | B168: 230-0067 | C168: Large 90° Bend Standard | D168: 15
A169: Air Sampling — Fittings | B169: 230-0068 | C169: End Cap 25mm DX52125 | D169: 1
A170: Air Sampling — Fittings | B170: 230-0072 | C170: Pipe Clip Saddle GW50603 | D170: 4
A171: Air Sampling — Fittings | B171: 230-0121 | C171: Label Sampling Pipe Roll 200 | D171: 58
A172: Air Sampling — Fittings | B172: 230-0081 | C172: Sampling Point Kit 10mm Friction Fit | D172: 41
A173: Air Sampling — Fittings | B173: 230-0082 | C173: Sampling Point Kit 10mm Locking | D173: 45
A174: Air Sampling — Fittings | B174: 01-10-9040 | C174: T Pipe Connector 25mm PVC | D174: 9
A175: Conv. Sounders — VTG/VSO | B175: 4107-3001 | C175: VTG Sounder Red Shallow Base (AS7240-3) | D175: 107
A176: Conv. Sounders — VTG/VSO | B176: 4107-3002 | C176: VTG Sounder Red Deep Body (AS7240-3) | D176: 119
A177: Conv. Sounders — VTG/VSO | B177: 4107-3003 | C177: VTG Sounder White Shallow Body (AS7240-3) | D177: 107
... A307: Test Equipment | B307: 4112-2009 | C307: Ampac Loop Tester | D307: 2585

Sheet Want Access — EWP
A1: WANT ACCESS — EWP Hire Rates (AUD excl. GST) | Flamesafe Fire Protection | Effective 14 Apr 2026 | Valid until 30 Apr 2027
A2: Contact: 02 9603 8883 | hire@wantaccess.com.au | 35 Anzac Ave, Smeaton Grange NSW 2567 | Metro rates only — all other locations POA
A3: ⚠ Damage Waiver: 15% of hire cost only (no admin, PPSR or environmental levies) | Harnesses: $5/day or $10/week with each boom lift | Diesel: $4.75/L on-charge, $3.95/L supplied to site | Gas bottles: $69.50/bottle | Fuel levy: 23% on all transport (from 08.04.2026) | Call-out fuel surcharge: $25.00
A4: Category | B4: Type / Terrain | C4: Description | D4: Day Rate (AUD) | E4: Week Rate (AUD) | F4: Notes
A5: Vertical Lifts | B5: Electric | C5: 12ft (3.6m) Vertical | D5: 55 | E5: 120
A6: Vertical Lifts | B6: Electric | C6: 16ft (4.8m) Vertical | D6: 55 | E6: 120
A7: Vertical Lifts | B7: Electric | C7: 20ft (6.0m) Vertical | D7: 110 | E7: 190
A8: Vertical Lifts | B8: Electric | C8: 26ft (8m) Star 10 Vertical Mast | D8: 110 | E8: 380
A9: Vertical Lifts | B9: Push Around | C9: 34ft (10.4m) Vertical | D9: 130 | E9: 310
A10: Scissor Lifts | B10: Electric | C10: 15ft (4.5m) Scissor | D10: 55 | E10: 120
A11: Scissor Lifts | B11: Electric | C11: 15ft (4.5m) Micro Scissor | D11: 55 | E11: 120
A12: Scissor Lifts | B12: Electric | C12: 19ft (5.8m) Scissor | D12: 55 | E12: 120
A13: Scissor Lifts | B13: Electric | C13: 20ft (6.1m) Scissor | D13: 55 | E13: 120
A14: Scissor Lifts | B14: Electric | C14: 20ft (6.1m) Wide Scissor | D14: 90 | E14: 150
A15: Scissor Lifts | B15: Electric | C15: 26ft (7.9m) Narrow Scissor | D15: 80 | E15: 240
A16: Scissor Lifts | B16: Electric | C16: 26ft (7.9m) Scissor | D16: 80 | E16: 240
... A44: Forklifts & Telehandlers | B44: Gas & Rough Terrain | C44: 4T 17M Telehandler | D44: 480 | E44: 1400
A45: Attachments | C45: EQSS Secondary Scissor Lift Guarding | D45: 2.5 | E45: 5
A46: Attachments | C46: Electric Scissor Lift — Pipe Racks | D46: 8 | E46: 20
A47: Attachments | C47: Electric Scissor Lift — Board Carriers | D47: 8 | E47: 20
A48: Attachments | C48: Diesel Scissor Lift — Pipe Racks | D48: 15 | E48: 35
A49: Attachments | C49: Forklift — Rotator | D49: 30 | E49: 75
A50: Attachments | C50: 2.5T Telehandler — Rotator | D50: 30 | E50: 75
A51: Attachments | C51: 2.5T Telehandler — Jib | D51: 20 | E51: 55
A52: Attachments | C52: 3T & Over Telehandler — Rotator | D52: 35 | E52: 85
A53: Attachments | C53: 3T & Over Telehandler — Jib | D53: 25 | E53: 65
A54: Scaffold | B54: Aluminium Towers | C54: Aluminium Towers (minimum 1 week hire) | D54: N/A | E54: $45/vert. m | F54: $45 per vertical metre per week — minimum 1 week
A56: TRANSPORT — Each Way (Metro Only) | 23% Temporary Fuel Levy applies | Non-metro: POA
A57: Category / Equipment | C57: Description | D57: One-Way Transport (AUD) | F57: Notes
A58: Vertical Lifts | D58: 170 | E58: First unit; $140 each additional
A59: Electric Scissor to 26ft | D59: 170 | E59: First unit; $140 each additional
A60: Electric Scissor 32ft | D60: 185
A61: Electric Scissor 40ft | D61: 200
A62: Star 10 & Athena | D62: 215
A63: Diesel Scissor to 33ft | D63: 215
A64: Diesel Scissor 39ft | D64: 250
A65: Diesel Scissor 43ft | D65: 245
A66: Diesel Scissor 53ft | D66: 265
A67: Booms to 34ft | D67: 225
A68: Booms to 46ft | D68: 250
A69: Booms to 51ft | D69: 275
A70: Booms to 67ft | D70: 370
A71: Booms to 86ft | D71: 440
... A73: Booms to 150ft | D73: 570
A74: Booms to 180ft | D74: POA | E74: POA
A75: 1.8T/2.5T Forklift | D75: 220
A76: 2.5T Telehandler | D76: 260
A77: 3T Telehandler | D77: 280
A78: 3.5T Telehandler | D78: 315
A79: 4T Telehandler | D79: 370
A80: Nifty HR12 | D80: 200
A81: Attachments | D81: 170
A82: Scaffold | D82: 170

Sheet FireSense
A1: FIRESENSE Pty Ltd — Trade Price List (AUD excl. GST) | NSW 2026 Catalogue | Flamesafe Fire Protection customer pricing
A2: Contact: (02) 8850 2888 | sales@firesense.com.au | 18-20 Brookhollow Ave, Norwest NSW 2153 | All prices excl. GST and freight. # = rebates may apply. P.O.A = price on application.
A3: Category | B3: Product Code | C3: Description | D3: Trade Price (AUD) | E3: Notes
A4: Batteries & Ancillary | B4: BATT-1.2 | C4: Battery set 1.2ah (2x12v) | D4: 37
A5: Batteries & Ancillary | B5: BATT-100 | C5: Battery set 100ah (2x12v) | D5: 689.01
A6: Batteries & Ancillary | B6: BATT-12 | C6: Battery set 12ah (2x12v) | D6: 103.35
A7: Batteries & Ancillary | B7: BATT-120 | C7: Battery set 120ah (2x12v) | D7: 826.8
A8: Batteries & Ancillary | B8: BATT-12V-100-DC | C8: Battery 100ah Deep Cycle (1x12v) | D8: 319.68
A9: Batteries & Ancillary | B9: BATT-12V-120-DC | C9: Battery 120ah Deep Cycle (1x12v) | D9: 358.11
A10: Batteries & Ancillary | B10: BATT-12V-75-DC | C10: Battery 75ah Deep Cycle (1x12v) | D10: 262.03
A11: Batteries & Ancillary | B11: BATT-12V-85-DC | C11: Battery 85ah Deep Cycle (1x12v) | D11: 290.86
A12: Batteries & Ancillary | B12: BATT-150 | C12: Battery set 150ah (2x12v) | D12: 895.71
A13: Batteries & Ancillary | B13: BATT-18 | C13: Battery set 18ah (2x12v) | D13: 137.8
A14: Batteries & Ancillary | B14: BATT-2.3 | C14: Battery set 2.3ah (2x12v) | D14: 41.46
A15: Batteries & Ancillary | B15: BATT-200 | C15: Battery set 200ah (2x12v) | D15: 1240.21
... A178: Detectors & Modules | B178: INT-IR3 | C178: IR3 Flame Det - Alloy housing | D178: 4874
A179: Detectors & Modules | B179: LHD-105-W-100 | C179: Linear Heat Detection Cable - 100m Roll - White - 105 Degree C | E179: P.O.A
A180: Detectors & Modules | B180: LHD-68-R-100 | C180: Linear Heat Detection Cable - 100m Roll - Red - 68 Degree C | E180: P.O.A
A181: Detectors & Modules | B181: LHD-68-R-200 | C181: Linear Heat Detection Cable - 200m Roll - Red - 68 Degree C | E181: P.O.A
A182: Detectors & Modules | B182: LHD-68-R-500 | C182: Linear Heat Detection Cable - 500m Roll - Red - 68 Degree C | E182: P.O.A
A183: Detectors & Modules | B183: LHD-78-R-100 | C183: Linear Heat Detection Cable - 100m Roll - Red - 78 Degree C | E183: P.O.A
A184: Detectors & Modules | B184: LHD-88-W-100 | C184: Linear Heat Detection Cable - 100m Roll - White - 88 Degree C | E184: P.O.A
A185: Detectors & Modules | B185: LHD-LOCPLUS-CON | C185: LHD - Locator Plus Alarm Location and Interface Controller | D185: 1252.5
A186: Detectors & Modules | B186: LHD-LOCPLUS-EOL | C186: LHD - Locator Plus End Of Line Unit | D186: 447.32
A187: Detectors & Modules | B187: OLS-E-100 | C187: E-Type 100 Degree C Heat Detector Probe | D187: 251.52
A188: Detectors & Modules | B188: OLS-E-130 | C188: E-Type 130 Degree C Heat Detector Probe | D188: 270.5
A189: Detectors & Modules | B189: OLS-E-60 | C189: E-Type 60 Degree C Heat Detector Probe | D189: 242.02
A190: Detectors & Modules | B190: OSE-HPW | C190: OSE-HPW - Emitter - High power, wired at 24VDC | D190: 1053.31
A191: Detectors & Modules | B191: OSE-INST | C191: OSID-INST - OSID Installation Kit | D191: 359.21
A192: Detectors & Modules | B192: OSE-SP | C192: OSE-SP - Emitter - Standard power, battery version | D192: 478.59
A193: Detectors & Modules | B193: OSE-SPW | C193: OSE-SPW - Emitter - Standard power, wired at 24VDC | D193: 478.59
A194: Detectors & Modules | B194: OSI-10 | C194: OSI-10 - Imager - 7 degree coverage, 24VDC | D194: 992.71
A195: Detectors & Modules | B195: OSI-90 | C195: OSI-90 - Imager - 80 degree coverage, 24VDC | D195: 1023.02
A196: Detectors & Modules | B196: SS-2012-24 | C196: 2012/24AUSI 9-24v Photoelectric Smoke Alarm Temp-3 Sounder | D196: 92.14
... A252: Detectors & Modules | B252: SSF-PTI-951-W | C252: FPTI-951AUS - WHITE - FLASHSCAN 900 - Photo Thermal IR Detector | D252: 138.22
A253: Earth Cable LSZH Class 6 | B253: LSZH-10-1CE | C253: Earth Cable - 10mm - 1Core | E253: P.O.A
A254: Earth Cable LSZH Class 6 | B254: LSZH-120-1CE | C254: Earth Cable - 120mm - 1Core - Per Meter | E254: P.O.A
A255: Earth Cable LSZH Class 6 | B255: LSZH-16-1CE | C255: Earth Cable - 16mm - 1Core - Per Meter | E255: P.O.A
A256: Earth Cable LSZH Class 6 | B256: LSZH-2.50-1CE | C256: Earth Cable - 2.50mm - 1Core (Indent Only) | E256: P.O.A
A257: Earth Cable LSZH Class 6 | B257: LSZH-25-1CE | C257: Earth Cable - 25mm - 1Core - Per Meter | E257: P.O.A
A258: Earth Cable LSZH Class 6 | B258: LSZH-35-1CE | C258: Earth Cable - 35mm - 1Core - Per Meter | E258: P.O.A
A259: Earth Cable LSZH Class 6 | B259: LSZH-4.00-1CE | C259: Earth Cable - 4.00mm - 1Core (Indent Only) | E259: P.O.A
A260: Earth Cable LSZH Class 6 | B260: LSZH-50-1CE | C260: Earth Cable - 50mm - 1Core - Per Meter | E260: P.O.A
A261: Earth Cable LSZH Class 6 | B261: LSZH-6.00-1CE | C261: Earth Cable - 6.00mm - 1Core | E261: P.O.A
A262: Earth Cable LSZH Class 6 | B262: LSZH-70-1CE | C262: Earth Cable - 70mm - 1Core - Per Meter | E262: P.O.A
A263: Earth Cable LSZH Class 6 | B263: LSZH-95-1CE | C263: Earth Cable - 95mm - 1Core - Per Meter | E263: P.O.A
A264: FR Cable — Detection 2C | B264: FR-0.75-2C | C264: Fire Rated Cable - 0.75mm - 2 Core | D264: 2.44
A265: FR Cable — Detection 2C | B265: FR-0.75-2C-250 | C265: Fire Rated Cable - 0.75mm - 2 Core - 250m Roll | D265: 610
A266: FR Cable — Detection 2C | B266: FR-0.75-2C-500 | C266: Fire Rated Cable - 0.75mm - 2 Core - 500m Roll | D266: 1220
A267: FR Cable — Detection 2C | B267: FR-1.00-2C | C267: Fire Rated Cable - 1.00mm - 2 Core | D267: 2.37
A268: FR Cable — Detection 2C | B268: FR-1.00-2C-250 | C268: Fire Rated Cable - 1.00mm - 2 Core - 250m Roll | D268: 592.5
A269: FR Cable — Detection 2C | B269: FR-1.00-2C-500 | C269: Fire Rated Cable - 1.00mm - 2 Core - 500m Roll | D269: 1185
A270: FR Cable — Detection 2C | B270: FR-1.50-2C | C270: Fire Rated Cable - 1.50mm - 2 Core | D270: 2.75
A271: FR Cable — Detection 2C | B271: FR-1.50-2C-250 | C271: Fire Rated Cable - 1.50mm - 2 Core - 250m Roll | D271: 687.5
A272: FR Cable — Detection 2C | B272: FR-1.50-2C-500 | C272: Fire Rated Cable - 1.50mm - 2 Core - 500m Roll | D272: 1375
A273: FR Cable — Detection 2C | B273: FR-2.50-2C | C273: Fire Rated Cable - 2.50mm - 2 Core | D273: 5.43
A274: FR Cable — Detection 2C | B274: FR-2.50-2C-250 | C274: Fire Rated Cable - 2.50mm - 2 Core - 250m Roll | D274: 1358.3
A275: FR Cable — Detection 2C | B275: FR-2.50-2C-500 | C275: Fire Rated Cable - 2.50mm - 2 Core - 500m Roll | D275: 2716.6
... A307: FR Cable — Power Class 2 Multicore | B307: FR-0.75-8CS | C307: Fire Rated Cable - 0.75mm - 8 Core Screened | D307: 12.36
A308: FR Cable — Power Class 2 Multicore | B308: FR-2.50-2C+E | C308: Fire Rated Cable - 2.50mm - 2 Core + 2.50mm2 Earth | E308: P.O.A
A309: FR Cable — Power Class 2 Multicore | B309: FR-2.50-3C+E | C309: Fire Rated Cable - 2.50mm - 3 Core + 2.50mm2 Earth | E309: P.O.A
A310: FR Cable — Power Class 2 Multicore | B310: FR-2.50-3C+ES | C310: Fire Rated Cable - 2.50mm - 3 Core + 2.50mm2 Earth Screened | E310: P.O.A
A311: FR Cable — Power Class 2 Multicore | B311: FR-2.50-4C+E | C311: Fire Rated Cable - 2.50mm - 4 Core + 2.50mm2 Earth | E311: P.O.A
A312: FR Cable — Power Class 2 Multicore | B312: FR-4.00-2C+E | C312: Fire Rated Cable - 4.00mm - 2 Core + 2.50mm2 Earth | E312: P.O.A
A313: FR Cable — Power Class 2 Multicore | B313: FR-4.00-3C+E | C313: Fire Rated Cable - 4.00mm - 3 Core + 2.50mm2 Earth | E313: P.O.A
A314: FR Cable — Power Class 2 Multicore | B314: FR-4.00-3C+ES | C314: Fire Rated Cable - 4.00mm - 3 Core + 2.50mm2 Earth Screened | E314: P.O.A
A315: FR Cable — Power Class 2 Multicore | B315: FR-4.00-4C+E | C315: Fire Rated Cable - 4.00mm - 4 Core + 2.50mm2 Earth | E315: P.O.A
A316: FR Cable — Power Class 2 Multicore | B316: FR-6.00-2C+E | C316: Fire Rated Cable - 6.00mm - 2 Core + 2.50mm2 Earth | E316: P.O.A
A317: FR Cable — Power Class 2 Multicore | B317: FR-6.00-3C+E | C317: Fire Rated Cable - 6.00mm - 3 Core + 2.50mm2 Earth | E317: P.O.A
A318: FR Cable — Power Class 2 Multicore | B318: FR-6.00-3C+ES | C318: Fire Rated Cable - 6.00mm - 3 Core + 2.50mm2 Earth Screened | E318: P.O.A
A319: FR Cable — Power Class 2 Multicore | B319: FR-6.00-4C+E | C319: Fire Rated Cable - 6.00mm - 4 Core + 2.50mm2 Earth | E319: P.O.A
... A343: FR Cable — Power Class 6 Single Core | B343: FR-95-1C | C343: Fire Rated Cable - 95mm - 1 Core | E343: P.O.A
A344: Misc / No Discounts | B344: FR-1.50-2CX | C344: Fire Rated Cable - 1.50mm - 2 Core - Comms -16 Twists pm | D344: 4.1
A345: Misc / No Discounts | B345: FR-1.50-2CX-500 | C345: Fire Rated Cable - 1.50mm - 2 Core - Comms - 500m Roll | D345: 2050
A346: Misc / No Discounts | B346: STI-1280 | C346: STI-1280 Weather Stopper Back Plate for STI-3150 Increases to IP54 | D346: 55
A347: Misc / No Discounts | B347: STI-3002 | C347: STI-3002 Weather Stopper Gasket for STI-3150 Increases to IP54 | D347: 30
A348: Misc / No Discounts | B348: VSP-PIP-024 | C348: PIP-024 - Non Return Valve for Pipework | D348: 90
A349: Misc / No Discounts | B349: VSP-PURG-2 | C349: FAAST Purging System AFE70-2 (Low Flow) | D349: 1750
A350: Misc / No Discounts | B350: VSP-PURG-3 | C350: FAAST Purging System AFE70-3 (High Flow and sub-zero temperatures) | D350: 2450
A351: Panels & Accessories | B351: 1600-650-11A | C351: FS-1600, 8 Zone, PS-11, In 650 Cabinet | D351: 1419.08
A352: Panels & Accessories | B352: 1600-650-11A-G | C352: FS-1600, 8 Zone, PS-11, Gas Module with Stop Gas, In 650 Cabinet | D352: 2465.58
A353: Panels & Accessories | B353: 1600-650-5A | C353: FS-1600, 8 Zone, PS-5, In 650 Cabinet | D353: 1195.43
A354: Panels & Accessories | B354: 1600-650-5A-30WDA2 | C354: FS-1600, 8 Zone, PS-5, 30w DA2 OWS, Mic, In 650 Cabinet | D354: 2053.97
A355: Panels & Accessories | B355: 1600-900-11A | C355: FS-1600, 8 Zone, PS-11, In 900 Cabinet | D355: 1867.86
... A360: Panels & Accessories | B360: 3030&VE-USB-CABLE | C360: 3030 and VESDA-E series USB Programming Cable - 3.0M | D360: 29.89
A361: Panels & Accessories | B361: 3030-18U-11A | C361: 3030 1 Loop, PS-11, Display, In 18u Window Cabinet | E361: P.O.A
A362: Panels & Accessories | B362: 3030-28U-11A | C362: 3030 1 Loop, PS-11, Display, In 28u Window Cabinet | E362: P.O.A
A363: Panels & Accessories | B363: 3030-40U-11A | C363: 3030 1 Loop, PS-11, Display, In 40u Window Cabinet | E363: P.O.A
A364: Panels & Accessories | B364: 3030-650-11A | C364: 3030 1 Loop, PS-11, Display, In 650 Window Cabinet | D364: 4049.52
A365: Panels & Accessories | B365: 3030-650-11A-G | C365: 3030 1 Loop PS-11 Display Gas Module with Stop Gas In 650 Cabinet | D365: 5379.44
A366: Panels & Accessories | B366: 3030-650-5A | C366: 3030 1 Loop, PS-5, Display, In 650 Window Cabinet | D366: 3639.84
A367: Panels & Accessories | B367: 3030-650-5A-30WDA2 | C367: 3030 1 Loop, PS-5, Display, 30w DA2 OWS, Mic In 650 Window Cabinet | D367: 3597.16
A368: Panels & Accessories | B368: 3030-900-11A | C368: 3030 1 Loop, PS-11, Display, In 900 Window Cabinet | D368: 4357.9
A369: Panels & Accessories | B369: 3030-900-11A-G | C369: 3030 1 Loop PS-11 Display Gas Module with Stop Gas In 900 Cabinet | D369: 5618.53
A370: Panels & Accessories | B370: 3030-900-5A | C370: 3030 1 Loop, PS-5, Display, In 900 Window Cabinet | D370: 4124.24
A371: Panels & Accessories | B371: 3030-ACM-24AT | C371: ACM-24AT - Control annunciator 24 buttons, 48 LED indications | D371: 821.86
A372: Panels & Accessories | B372: 3030-ACM-48A | C372: ACM-48A - Annunciator (control) 48 x LED indications | D372: 672.44
A373: Panels & Accessories | B373: 3030-AEM-24AT | C373: AEM-24AT - Expansion annunciator 24 buttons, 48 LED indications | D373: 747.15
A374: Panels & Accessories | B374: 3030-AEM-48A | C374: AEM-48A - Annunciator (expander) 48 x LED indications | D374: 597.72
A375: Panels & Accessories | B375: 3030-BB-18U | C375: 3030-BB-18U - Battery box to suit 18U Fire Panel - Black | D375: 565.12
...

Sheet ESA — EWP
A1: ERECT SAFE ACCESS — EWP Hire Quote ESA1728 (AUD) | Flamesafe Fire Protection | Quoted 24 February 2026 | Valid 30 days unless specified
A2: Contact: Maxine Butler — 0427 482 631 | Sydney Metro only (other areas POA) | Daily rate first 3 days, weekly pro-rata from day 4 | Diesel return-fill $3.50/L | All Plant complies with EWPAA Standards with logbooks
A3: ⚠ Insurance Levy: 12% (waived if valid COC provided) | Environmental Levy: 1% | GST: 10% applied to (rate + levies) | Boom lifts: 2× safety harnesses @ $5 each per day/week | Transport (+ GST) within Sydney Metro only
A4: Category | B4: Machine Type | C4: Hire Cycle | D4: Base Rate (AUD) | E4: Insurance Levy 12% | F4: Enviro Levy 1% | G4: GST | H4: Total Inc GST (AUD)
A5: Electric Scissor | B5: 19ft Electric Scissor Lift | C5: Daily | D5: 100 | E5: =D5*0.12 -> 12 | F5: =D5*0.01 -> 1 | G5: =(D5+E5+F5)*0.1 -> 11.3 | H5: =D5+E5+F5+G5 -> 124.3
A6: Electric Scissor | B6: 19ft Electric Scissor Lift | C6: Weekly | D6: 120 | E6: =D6*0.12 -> 14.4 | F6: =D6*0.01 -> 1.2 | G6: =(D6+E6+F6)*0.1 -> 13.56 | H6: =D6+E6+F6+G6 -> 149.16
A7: Electric Scissor | B7: 26ft Electric Scissor Lift | C7: Daily | D7: 130 | E7: =D7*0.12 -> 15.6 | F7: =D7*0.01 -> 1.3 | G7: =(D7+E7+F7)*0.1 -> 14.69 | H7: =D7+E7+F7+G7 -> 161.59
A8: Electric Scissor | B8: 26ft Electric Scissor Lift | C8: Weekly | D8: 240 | E8: =D8*0.12 -> 28.8 | F8: =D8*0.01 -> 2.4 | G8: =(D8+E8+F8)*0.1 -> 27.12 | H8: =D8+E8+F8+G8 -> 298.32
A9: Electric Scissor | B9: 32ft Electric Scissor Lift | C9: Daily | D9: 140 | E9: =D9*0.12 -> 16.8 | F9: =D9*0.01 -> 1.4 | G9: =(D9+E9+F9)*0.1 -> 15.82 | H9: =D9+E9+F9+G9 -> 174.02
A10: Electric Scissor | B10: 32ft Electric Scissor Lift | C10: Weekly | D10: 280 | E10: =D10*0.12 -> 33.6 | F10: =D10*0.01 -> 2.8 | G10: =(D10+E10+F10)*0.1 -> 31.64 | H10: =D10+E10+F10+G10 -> 348.04
A11: Electric Scissor | B11: 40ft Electric Scissor Lift | C11: Daily | D11: 250 | E11: =D11*0.12 -> 30 | F11: =D11*0.01 -> 2.5 | G11: =(D11+E11+F11)*0.1 -> 28.25 | H11: =D11+E11+F11+G11 -> 310.75
A12: Electric Scissor | B12: 40ft Electric Scissor Lift | C12: Weekly | D12: 500 | E12: =D12*0.12 -> 60 | F12: =D12*0.01 -> 5 | G12: =(D12+E12+F12)*0.1 -> 56.5 | H12: =D12+E12+F12+G12 -> 621.5
A13: Electric Knuckle Boom | B13: 30/34ft Electric Knuckle Boom | C13: Daily | D13: 200 | E13: =D13*0.12 -> 24 | F13: =D13*0.01 -> 2 | G13: =(D13+E13+F13)*0.1 -> 22.6 | H13: =D13+E13+F13+G13 -> 248.6
A14: Electric Knuckle Boom | B14: 30/34ft Electric Knuckle Boom | C14: Weekly | D14: 600 | E14: =D14*0.12 -> 72 | F14: =D14*0.01 -> 6 | G14: =(D14+E14+F14)*0.1 -> 67.8 | H14: =D14+E14+F14+G14 -> 745.8
A15: Electric Knuckle Boom | B15: 45ft Electric Knuckle Boom | C15: Daily | D15: 250 | E15: =D15*0.12 -> 30 | F15: =D15*0.01 -> 2.5 | G15: =(D15+E15+F15)*0.1 -> 28.25 | H15: =D15+E15+F15+G15 -> 310.75
A16: Electric Knuckle Boom | B16: 45ft Electric Knuckle Boom | C16: Weekly | D16: 750 | E16: =D16*0.12 -> 90 | F16: =D16*0.01 -> 7.5 | G16: =(D16+E16+F16)*0.1 -> 84.75 | H16: =D16+E16+F16+G16 -> 932.25
A18: Transport — Sydney Metro (+ GST)
A19: Category | B19: Machine Type | C19: To Site (excl GST) | D19: Cost | E19: From Site (excl GST) | F19: Cost
A20: Electric Scissor | B20: 19ft Electric Scissor Lift | C20: To Site | D20: 165 | E20: Return / off-hire from site | F20: 165
A21: Electric Scissor | B21: 26ft Electric Scissor Lift | C21: To Site | D21: 165 | E21: Return / off-hire from site | F21: 165
A22: Electric Scissor | B22: 32ft Electric Scissor Lift | C22: To Site | D22: 165 | E22: Return / off-hire from site | F22: 165
A23: Electric Scissor | B23: 40ft Electric Scissor Lift | C23: To Site | D23: 200 | E23: Return / off-hire from site | F23: 200
A24: Electric Knuckle Boom | B24: 30/34ft Electric Knuckle Boom | C24: To Site | D24: 221 | E24: Return / off-hire from site | F24: 221
A25: Electric Knuckle Boom | B25: 45ft Electric Knuckle Boom | C25: To Site | D25: 240 | E25: Return / off-hire from site | F25: 240
